{"inputUnits":[5],"outputUnits":22,"inputs":{"v00":{"dtype":"number","min":20,"max":100},"v01":{"dtype":"number","min":20,"max":100},"v02":{"dtype":"number","min":20,"max":100},"v03":{"dtype":"number","min":20,"max":100},"v04":{"dtype":"number","min":20,"max":100}},"outputs":{"sClass":{"dtype":"string","min":0,"max":1,"uniqueValues":["Paladin!?!protection-p","Priest!?!shadow","hunter!?!devilhunter","fighter!?!soulmaster","hunter!?!hawkeye","warrior!?!destroyer","hunter!?!blaster","assassin!?!demonic","fighter!?!battlemaster","assassin!?!reaper","warrior!?!berserker","magician!?!arcana","fighter!?!striker","magician!?!summoner","fighter!?!infighter","hunter!?!scouter","fighter!?!lancemaster","warrior!?!warlord","hunter!?!gunslinger","warrior!?!holyknight","assassin!?!blade","magician!?!bard"],"legend":{"Paladin!?!protection-p":[1,0,0,0,0,0,0,0,0,0,0,0,0,0,0,0,0,0,0,0,0,0],"Priest!?!shadow":[0,1,0,0,0,0,0,0,0,0,0,0,0,0,0,0,0,0,0,0,0,0],"hunter!?!devilhunter":[0,0,1,0,0,0,0,0,0,0,0,0,0,0,0,0,0,0,0,0,0,0],"fighter!?!soulmaster":[0,0,0,1,0,0,0,0,0,0,0,0,0,0,0,0,0,0,0,0,0,0],"hunter!?!hawkeye":[0,0,0,0,1,0,0,0,0,0,0,0,0,0,0,0,0,0,0,0,0,0],"warrior!?!destroyer":[0,0,0,0,0,1,0,0,0,0,0,0,0,0,0,0,0,0,0,0,0,0],"hunter!?!blaster":[0,0,0,0,0,0,1,0,0,0,0,0,0,0,0,0,0,0,0,0,0,0],"assassin!?!demonic":[0,0,0,0,0,0,0,1,0,0,0,0,0,0,0,0,0,0,0,0,0,0],"fighter!?!battlemaster":[0,0,0,0,0,0,0,0,1,0,0,0,0,0,0,0,0,0,0,0,0,0],"assassin!?!reaper":[0,0,0,0,0,0,0,0,0,1,0,0,0,0,0,0,0,0,0,0,0,0],"warrior!?!berserker":[0,0,0,0,0,0,0,0,0,0,1,0,0,0,0,0,0,0,0,0,0,0],"magician!?!arcana":[0,0,0,0,0,0,0,0,0,0,0,1,0,0,0,0,0,0,0,0,0,0],"fighter!?!striker":[0,0,0,0,0,0,0,0,0,0,0,0,1,0,0,0,0,0,0,0,0,0],"magician!?!summoner":[0,0,0,0,0,0,0,0,0,0,0,0,0,1,0,0,0,0,0,0,0,0],"fighter!?!infighter":[0,0,0,0,0,0,0,0,0,0,0,0,0,0,1,0,0,0,0,0,0,0],"hunter!?!scouter":[0,0,0,0,0,0,0,0,0,0,0,0,0,0,0,1,0,0,0,0,0,0],"fighter!?!lancemaster":[0,0,0,0,0,0,0,0,0,0,0,0,0,0,0,0,1,0,0,0,0,0],"warrior!?!warlord":[0,0,0,0,0,0,0,0,0,0,0,0,0,0,0,0,0,1,0,0,0,0],"hunter!?!gunslinger":[0,0,0,0,0,0,0,0,0,0,0,0,0,0,0,0,0,0,1,0,0,0],"warrior!?!holyknight":[0,0,0,0,0,0,0,0,0,0,0,0,0,0,0,0,0,0,0,1,0,0],"assassin!?!blade":[0,0,0,0,0,0,0,0,0,0,0,0,0,0,0,0,0,0,0,0,1,0],"magician!?!bard":[0,0,0,0,0,0,0,0,0,0,0,0,0,0,0,0,0,0,0,0,0,1]}}},"isNormalized":true}